{
  "meta": {
    "destination": "dest49",
    "title": "El mapa de las voces",
    "cefr": "C2",
    "world": "mundoDeArriba",
    "campbellStage": "Return — the elixir is knowledge of the whole",
    "characters": [
      "char_yaguara",
      "char_candelaria",
      "char_rio",
      "char_colibri",
      "char_condor_viejo",
      "char_delfin_rosado",
      "char_tortuga_marina"
    ],
    "grammarTargets": [
      "register mastery: colloquial → formal → literary",
      "sociolinguistic variation: diatopic (costeño/paisa/rolo)",
      "code-switching across registers",
      "pragmatic competence at native level",
      "dialectal comprehension and production"
    ],
    "coreVocabulary": [
      "registro",
      "variante",
      "dialecto",
      "jerga",
      "coloquial",
      "formal",
      "literario",
      "pragmática",
      "diatopía",
      "sociolecto",
      "idiolecto",
      "hablante",
      "interlocutor",
      "entonación"
    ],
    "narrativeVocabulary": [
      "mapa",
      "voz",
      "coro",
      "guía",
      "reunión",
      "camino",
      "memoria",
      "territorio",
      "escucha",
      "habla",
      "canto",
      "palabra"
    ]
  },
  "ecosystemVocabulary": {
    "bosque": {
      "animal": [
        "quetzal",
        "ocelote",
        "coatí",
        "trogón",
        "salamandra",
        "escarabajo",
        "murciélago",
        "serpiente coral"
      ],
      "nature": [
        "epífita",
        "bromelia",
        "niebla",
        "raíz aérea",
        "musgo luminoso",
        "helecho arbóreo",
        "micorriza"
      ],
      "place": [
        "dosel",
        "sotobosque",
        "claroscuro",
        "vertiente",
        "manantial"
      ],
      "sound": [
        "goteo",
        "crujido",
        "aleteo",
        "murmullo",
        "silbo"
      ],
      "texture": [
        "musgoso",
        "húmedo",
        "penumbroso",
        "aterciopelado",
        "esponjoso"
      ]
    },
    "costa": {
      "animal": [
        "fragata",
        "raya águila",
        "tortuga carey",
        "barracuda",
        "cangrejo violinista",
        "pelícano pardo",
        "medusa",
        "pez loro"
      ],
      "nature": [
        "manglar",
        "salitre",
        "espuma",
        "resaca",
        "pleamar",
        "coral cerebro",
        "alga"
      ],
      "place": [
        "estuario",
        "rompeolas",
        "marisma",
        "ensenada",
        "fondeadero"
      ],
      "sound": [
        "oleaje",
        "graznido",
        "marejada",
        "chapoteo",
        "brisa salina"
      ],
      "texture": [
        "salitroso",
        "iridiscente",
        "erosionado",
        "calcáreo",
        "nacarado"
      ]
    },
    "desierto": {
      "animal": [
        "correcaminos",
        "víbora cornuda",
        "escorpión dorado",
        "lagarto cornudo",
        "búho madriguero",
        "halcón peregrino",
        "tarántula",
        "gecko"
      ],
      "nature": [
        "dunas",
        "espejismo",
        "pedregal",
        "oasis",
        "crepúsculo",
        "líquen",
        "cardón"
      ],
      "place": [
        "barranco",
        "meseta",
        "salina",
        "erg",
        "wadi"
      ],
      "sound": [
        "silbido",
        "crepitar",
        "aullido",
        "susurro de arena",
        "eco mineral"
      ],
      "texture": [
        "reseco",
        "abrasivo",
        "incandescente",
        "polvoriento",
        "cristalino"
      ]
    },
    "islas": {
      "animal": [
        "iguana marina",
        "piquero patiazul",
        "tortuga gigante",
        "tiburón martillo",
        "lobo marino",
        "albatros",
        "cangrejo rojo",
        "mantarraya"
      ],
      "nature": [
        "lava solidificada",
        "arrecife",
        "corriente",
        "atolón",
        "fitoplancton",
        "sargazo",
        "caleta"
      ],
      "place": [
        "islote",
        "farallón",
        "laguna",
        "archipiélago",
        "cráter"
      ],
      "sound": [
        "rompiente",
        "graznido",
        "chapuzón",
        "silencio oceánico",
        "viento insular"
      ],
      "texture": [
        "volcánico",
        "prístino",
        "ultramarino",
        "basáltico",
        "transparente"
      ]
    },
    "llanos": {
      "animal": [
        "chigüiro",
        "anaconda",
        "garza morena",
        "caimán del Orinoco",
        "venado caramerudo",
        "araguato",
        "corocora",
        "galápago"
      ],
      "nature": [
        "estero",
        "morichal",
        "sabana inundable",
        "caño",
        "banco de arena",
        "palma moriche",
        "gramínea"
      ],
      "place": [
        "hato",
        "médano",
        "paso",
        "vega",
        "lindero"
      ],
      "sound": [
        "arpa llanera",
        "mugido",
        "relincho",
        "galope",
        "canto de alcaraván"
      ],
      "texture": [
        "anegado",
        "arcilloso",
        "abierto",
        "tórrido",
        "ondulante"
      ]
    },
    "nevada": {
      "animal": [
        "cóndor",
        "oso de anteojos",
        "colibrí estrella",
        "danta de montaña",
        "puma",
        "águila crestada",
        "rana arlequín",
        "venado páramo"
      ],
      "nature": [
        "frailejón gigante",
        "turbera",
        "glaciar",
        "laguna de origen",
        "niebla perpetua",
        "liquen saxícola",
        "páramo"
      ],
      "place": [
        "morrena",
        "circo glaciar",
        "collado",
        "abrigo rocoso",
        "cumbre"
      ],
      "sound": [
        "ventisca",
        "deshielo",
        "silencio glaciar",
        "eco de abismo",
        "canto de cóndor"
      ],
      "texture": [
        "gélido",
        "mineral",
        "ralo",
        "cristalino",
        "imponente"
      ]
    },
    "selva": {
      "animal": [
        "jaguar melanístico",
        "guacamaya bandera",
        "delfín rosado",
        "anaconda verde",
        "rana dardo",
        "mono aullador",
        "tucán esmeralda",
        "tapir"
      ],
      "nature": [
        "ceiba",
        "liana",
        "orquídea",
        "raíz tabular",
        "humus",
        "hojarasca",
        "dosel cerrado"
      ],
      "place": [
        "maloca",
        "raudal",
        "várzea",
        "igapó",
        "claro ceremonial"
      ],
      "sound": [
        "aullido",
        "torrente",
        "chasquido",
        "rugido",
        "gota sobre hoja"
      ],
      "texture": [
        "exuberante",
        "fértil",
        "umbrío",
        "sofocante",
        "rezumante"
      ]
    },
    "sierra": {
      "animal": [
        "mula arriera",
        "colibrí chivito",
        "gallina ciega",
        "perro criollo",
        "armadillo",
        "zorro perruno",
        "turpial",
        "toche"
      ],
      "nature": [
        "cafetal",
        "guadua",
        "bruma",
        "arcilla roja",
        "piedra musgosa",
        "helecho",
        "orquídea silvestre"
      ],
      "place": [
        "vereda",
        "trapiche",
        "tapia",
        "camino real",
        "mirador"
      ],
      "sound": [
        "tiple",
        "campana",
        "arriero",
        "arroyo",
        "gallo de madrugada"
      ],
      "texture": [
        "templado",
        "terroso",
        "empedrado",
        "ahumado",
        "ancestral"
      ]
    }
  },
  "templates": [
    {
      "_template": {
        "id": "T01_skit_voices_gather",
        "layer": "narrative",
        "order": 1,
        "description": "All guides gather. Each speaks in their register — colloquial, formal, literary — and the map of voices begins to form.",
        "spiralReturn": [
          5,
          13
        ],
        "inputModes": [
          "choice"
        ],
        "ecosystemSlots": [
          "animal",
          "nature",
          "place",
          "sound"
        ]
      },
      "type": "skit",
      "label": "Escena",
      "title": "El coro de los guías",
      "instruction": "Escucha las voces. Identifica los registros.",
      "grammar": [
        "register mastery"
      ],
      "beats": [
        {
          "speaker": "narrator",
          "name": "Narrador",
          "animation": "fade-in",
          "text": "Uno a uno llegan. El {pool:eco.animal}, el {pool:eco.animal}, el {pool:eco.animal} rosado, la {pool:eco.animal} marina. Las voces del viaje entero reunidas en un solo claro."
        },
        {
          "speaker": "colibri",
          "name": "Colibrí",
          "animation": "glow",
          "text": "Oye, parcera, aquí andamos otra vez. ¿Te acuerdas de la primera palabra que aprendiste? Yo sí me acuerdo, ¡uy, qué tiempos!",
          "target": [
            "parcera",
            "aquí andamos",
            "¡uy, qué tiempos!"
          ]
        },
        {
          "speaker": "condor_viejo",
          "name": "Cóndor Viejo",
          "animation": "fade-in",
          "text": "Permítame señalar, con el debido respeto, que la memoria no es un repositorio pasivo sino un acto deliberado de reconstrucción.",
          "target": [
            "Permítame señalar",
            "con el debido respeto",
            "repositorio"
          ]
        },
        {
          "speaker": "delfin_rosado",
          "name": "Delfín Rosado",
          "animation": "glow",
          "text": "Y en el fondo del {pool:eco.place}, donde la lengua se deshace en espuma, la palabra no se dice: se presiente, se intuye, se sueña antes de ser {pool:eco.sound}.",
          "target": [
            "se presiente",
            "se intuye",
            "se sueña"
          ]
        },
        {
          "speaker": "yaguara",
          "name": "Yaguará",
          "animation": "glow",
          "text": "Tres registros. Tres formas de nombrar lo mismo. ¿Cuál de ellos habló en registro coloquial?",
          "interaction": {
            "type": "pick",
            "options": [
              "Colibrí — coloquial, cercano, lleno de marcadores regionales",
              "Cóndor Viejo — formal, distanciado, con léxico técnico",
              "Delfín Rosado — literario, poético, con imágenes sensoriales"
            ],
            "answer": "Colibrí — coloquial, cercano, lleno de marcadores regionales"
          }
        },
        {
          "speaker": "candelaria",
          "name": "Candelaria",
          "animation": "fade-in",
          "text": "Cada voz dibuja un {pool:eco.place}. El mapa no es de {pool:eco.nature}: es de hablas, de tonos, de silencios. Y ahora lo vamos a trazar."
        },
        {
          "speaker": "narrator",
          "name": "Narrador",
          "animation": "glow",
          "text": "El mapa de las voces se enciende. Cada guía aporta su registro, su variante, su dialecto. El C2 comienza."
        }
      ]
    },
    {
      "_template": {
        "id": "T02_skit_dialectal_encounter",
        "layer": "narrative",
        "order": 2,
        "description": "Diatopic variation: costeño, paisa, rolo. Three voices, one meaning, three territorios lingüísticos.",
        "spiralReturn": [
          3,
          8
        ],
        "inputModes": [
          "choice"
        ],
        "ecosystemSlots": [
          "nature",
          "place"
        ]
      },
      "type": "skit",
      "label": "Escena",
      "title": "Tres territorios, una lengua",
      "instruction": "Identifica la variante dialectal de cada hablante.",
      "grammar": [
        "sociolinguistic variation: diatopic"
      ],
      "beats": [
        {
          "speaker": "narrator",
          "name": "Narrador",
          "animation": "fade-in",
          "text": "Tres sombras se acercan al claro. Cada una habla castellano, pero el castellano de cada una sabe distinto."
        },
        {
          "speaker": "voice_costeno",
          "name": "Voz costeña",
          "animation": "fade-in",
          "text": "Ajá, mira, ¿y tú qué? ¿Tú crees que hablar bonito es hablar como la gente de la capital? Aquí la lengua tiene sabor a {pool:eco.place}, vale.",
          "target": [
            "Ajá",
            "vale",
            "sabor a mar"
          ]
        },
        {
          "speaker": "voice_paisa",
          "name": "Voz paisa",
          "animation": "fade-in",
          "text": "Pues hombre, qué más, ¿cierto? Uno habla como le enseñaron en la finca, con las palabras que huelen a café y a {pool:eco.nature} de {pool:eco.place}.",
          "target": [
            "Pues hombre",
            "qué más",
            "¿cierto?"
          ]
        },
        {
          "speaker": "voice_rolo",
          "name": "Voz rola",
          "animation": "fade-in",
          "text": "Hermano, o sea, digamos que el español capitalino tiende a una formalidad que a veces confunden con frialdad, ¿me hago entender?",
          "target": [
            "Hermano",
            "o sea",
            "digamos que",
            "¿me hago entender?"
          ]
        },
        {
          "speaker": "yaguara",
          "name": "Yaguará",
          "animation": "glow",
          "text": "Ninguna variante es superior. El mapa de las voces no tiene centro. ¿Cuál de las tres usó el marcador discursivo '¿cierto?'?",
          "interaction": {
            "type": "pick",
            "options": [
              "La voz paisa",
              "La voz costeña",
              "La voz rola"
            ],
            "answer": "La voz paisa"
          }
        },
        {
          "speaker": "candelaria",
          "name": "Candelaria",
          "animation": "fade-in",
          "text": "Tres {pool:eco.place} desembocan en el mismo {pool:eco.place}. Entender las tres corrientes es habitar la lengua entera."
        }
      ]
    },
    {
      "_template": {
        "id": "T03_conversation_register_shift",
        "layer": "narrative",
        "order": 3,
        "description": "The student must shift register within a single conversation: from colloquial to formal to literary.",
        "spiralReturn": [
          5,
          13
        ],
        "inputModes": [
          "choice",
          "typing"
        ],
        "ecosystemSlots": [
          "place"
        ]
      },
      "type": "conversation",
      "label": "Conversación",
      "instruction": "Adapta tu registro según el interlocutor en {pool:eco.place}.",
      "tip": {
        "title": "Cambio de registro",
        "lines": [
          "Coloquial: muletillas, elisión, marcadores regionales (parcero, vale, ¿cierto?)",
          "Formal: distanciamiento, léxico preciso, cortesía indirecta",
          "Literario: imágenes, ritmo, polisemia, figuras retóricas"
        ]
      },
      "turns": [
        {
          "dialogue": [
            {
              "speaker": "A",
              "name": "Colibrí",
              "text": "Ey, parce, ¿cómo me explicarías qué es la nostalgia? Pero dímelo como se lo dirías a un amigo."
            },
            {
              "speaker": "B",
              "name": "Tú",
              "text": "???"
            }
          ],
          "options": [
            "Es como cuando extrañas algo un montón y te da esa cosa en el pecho, ¿me entiendes?",
            "La nostalgia se define como un sentimiento de añoranza respecto al pasado.",
            "La nostalgia es la herida que deja lo que fue y que el tiempo no consiente cerrar."
          ],
          "answer": "Es como cuando extrañas algo un montón y te da esa cosa en el pecho, ¿me entiendes?"
        },
        {
          "dialogue": [
            {
              "speaker": "A",
              "name": "Cóndor Viejo",
              "text": "Le ruego que formule una definición rigurosa del concepto de nostalgia para el acta."
            },
            {
              "speaker": "B",
              "name": "Tú",
              "text": "???"
            }
          ],
          "options": [
            "La nostalgia se define como un estado afectivo caracterizado por la añoranza de vivencias pasadas.",
            "Es esa vaina de extrañar, ¿sabe?",
            "La nostalgia es una hoja que cae sin que nadie la vea tocar el suelo."
          ],
          "answer": "La nostalgia se define como un estado afectivo caracterizado por la añoranza de vivencias pasadas."
        },
        {
          "dialogue": [
            {
              "speaker": "A",
              "name": "Delfín Rosado",
              "text": "Ahora dilo como si escribieras un poema. Haz que la palabra sangre."
            },
            {
              "speaker": "B",
              "name": "Tú",
              "text": "???"
            }
          ],
          "options": [
            "La nostalgia es la herida que deja lo que fue y que el tiempo no consiente cerrar.",
            "Es extrañar cosas viejas.",
            "La nostalgia constituye un fenómeno psicológico de carácter retrospectivo."
          ],
          "answer": "La nostalgia es la herida que deja lo que fue y que el tiempo no consiente cerrar."
        },
        {
          "dialogue": [
            {
              "speaker": "A",
              "name": "Yaguará",
              "text": "Tres registros. Una sola palabra. ¿Cuál es la diferencia esencial entre registro formal y literario?"
            },
            {
              "speaker": "B",
              "name": "Tú",
              "text": "???"
            }
          ],
          "options": [
            "El formal busca precisión y distancia; el literario busca resonancia y ambigüedad fértil.",
            "El formal es aburrido y el literario es bonito.",
            "No hay diferencia, son lo mismo."
          ],
          "answer": "El formal busca precisión y distancia; el literario busca resonancia y ambigüedad fértil."
        }
      ]
    },
    {
      "_template": {
        "id": "T04_conversation_code_switching",
        "layer": "narrative",
        "order": 4,
        "description": "Code-switching: moving between dialectal varieties in a single exchange. Pragmatic competence.",
        "spiralReturn": [
          4,
          11
        ],
        "inputModes": [
          "choice",
          "typing"
        ],
        "ecosystemSlots": [
          "place"
        ]
      },
      "type": "conversation",
      "label": "Conversación",
      "instruction": "Navega entre variantes dialectales según el contexto en {pool:eco.place}.",
      "turns": [
        {
          "dialogue": [
            {
              "speaker": "A",
              "name": "Tortuga Marina",
              "text": "Un pescador costeño te pregunta: '¿Pa' dónde vas, vale?' ¿Cómo le contestas en su variante?"
            },
            {
              "speaker": "B",
              "name": "Tú",
              "text": "???"
            }
          ],
          "options": [
            "Voy pa'l río, vale, a ver qué sale.",
            "Me dirijo al río con la intención de explorar.",
            "Camino hacia el agua primordial."
          ],
          "answer": "Voy pa'l río, vale, a ver qué sale."
        },
        {
          "dialogue": [
            {
              "speaker": "A",
              "name": "Tortuga Marina",
              "text": "Ahora un profesor bogotano te hace la misma pregunta: '¿Hacia dónde se dirige?'"
            },
            {
              "speaker": "B",
              "name": "Tú",
              "text": "???"
            }
          ],
          "options": [
            "Me dirijo al río para realizar una observación de campo.",
            "Voy pa'l río, profe.",
            "Donde el agua se hace palabra, ahí voy."
          ],
          "answer": "Me dirijo al río para realizar una observación de campo."
        },
        {
          "dialogue": [
            {
              "speaker": "A",
              "name": "Tortuga Marina",
              "text": "Ahora un arriero paisa te pregunta: '¿Pa' dónde va, hombre, que tan de afán?'"
            },
            {
              "speaker": "B",
              "name": "Tú",
              "text": "???"
            }
          ],
          "options": [
            "Voy bajando al río, pues, hombre, que hay que madrugarle al día.",
            "Procedo a descender hasta la cuenca fluvial.",
            "Me dirijo al río, vale, tranqui."
          ],
          "answer": "Voy bajando al río, pues, hombre, que hay que madrugarle al día."
        }
      ]
    },
    {
      "_template": {
        "id": "T05_eco_lejano_voces_territorio",
        "layer": "narrative",
        "order": 5,
        "description": "The distant echo: voices of the ecosystem speak in register and dialect. Landscape as linguistic territory.",
        "spiralReturn": [
          8,
          21
        ],
        "inputModes": [
          "choice"
        ],
        "ecosystemSlots": [
          "animal",
          "nature",
          "place",
          "sound"
        ]
      },
      "type": "eco_lejano",
      "label": "Eco lejano",
      "instruction": "Escucha el eco del territorio. Identifica el registro.",
      "text": "Desde el {pool:eco.place} llega una voz que arrastra el acento del paisaje. El {pool:eco.animal} no habla castellano: habla territorio, habla {pool:eco.sound}, habla la variante de quienes nacieron oyendo el {pool:eco.nature}. Toda lengua es hija de un lugar.",
      "question": "¿Qué quiere decir que 'toda lengua es hija de un lugar'?",
      "answer": "Que las variantes dialectales nacen del territorio, de la geografía, del paisaje que moldea el habla.",
      "options": [
        "Que las variantes dialectales nacen del territorio, de la geografía, del paisaje que moldea el habla.",
        "Que cada idioma tiene un solo lugar correcto.",
        "Que los animales hablan el mismo idioma que los humanos."
      ]
    },
    {
      "_template": {
        "id": "T06_listening_register_identification",
        "layer": "narrative",
        "order": 6,
        "description": "Listening comprehension at C2: identify register, dialectal markers, and pragmatic intent.",
        "spiralReturn": [
          5,
          13
        ],
        "inputModes": [
          "choice",
          "typing"
        ],
        "ecosystemSlots": [
          "nature"
        ]
      },
      "type": "listening",
      "label": "Escuchar",
      "instruction": "Escucha e identifica el registro y la intención pragmática.",
      "questions": [
        {
          "audio": "Mire, doctor, con todo respeto, lo que usted propone no se ajusta al marco normativo vigente.",
          "question": "¿Qué registro usa este hablante?",
          "answer": "Formal-institucional con cortesía mitigadora",
          "options": [
            "Formal-institucional con cortesía mitigadora",
            "Coloquial costeño",
            "Literario poético"
          ]
        },
        {
          "audio": "Eche, mijo, eso que tú dices suena bonito pero aquí la cosa es otra, ¿oíste?",
          "question": "¿Qué variante dialectal predomina?",
          "answer": "Costeña (caribeña colombiana)",
          "options": [
            "Costeña (caribeña colombiana)",
            "Paisa (antioqueña)",
            "Rola (bogotana)"
          ]
        },
        {
          "audio": "Las palabras, cuando las sueltas al {pool:eco.nature}, no vuelven: se quedan flotando como {pool:eco.nature} que no saben dónde caer.",
          "question": "¿Qué tipo de registro es este?",
          "answer": "Literario — uso de símil extendido y personificación",
          "options": [
            "Literario — uso de símil extendido y personificación",
            "Formal académico",
            "Coloquial informal"
          ]
        },
        {
          "audio": "Pues uno no sabe, ¿cierto? Porque vea, la vida es así, como muy rara, como muy pues... como muy todo.",
          "question": "¿Qué variante dialectal se percibe?",
          "answer": "Paisa — muletillas (pues, ¿cierto?, vea) y circunloquio",
          "options": [
            "Paisa — muletillas (pues, ¿cierto?, vea) y circunloquio",
            "Costeña — elisiones y acento caribeño",
            "Formal — léxico técnico y distanciamiento"
          ]
        }
      ]
    },
    {
      "_template": {
        "id": "T07_skit_map_unfolds",
        "layer": "narrative",
        "order": 7,
        "description": "The map of voices unfolds. Every guide contributes a coordinate. The full linguistic atlas of the journey.",
        "spiralReturn": [
          3,
          8
        ],
        "inputModes": [
          "choice"
        ],
        "ecosystemSlots": [
          "sound"
        ]
      },
      "type": "skit",
      "label": "Escena",
      "title": "El mapa se despliega",
      "instruction": "Observa cómo cada guía añade su coordenada al mapa.",
      "beats": [
        {
          "speaker": "narrator",
          "name": "Narrador",
          "animation": "fade-in",
          "text": "El mapa flota en el aire entre los guías. No tiene fronteras dibujadas: tiene ondas de {pool:eco.sound}, capas de registro, corrientes de dialecto."
        },
        {
          "speaker": "tortuga_marina",
          "name": "Tortuga Marina",
          "animation": "glow",
          "text": "Yo traigo la paciencia del habla antigua: las palabras que tardan en llegar porque vienen de muy hondo.",
          "target": [
            "habla antigua",
            "muy hondo"
          ]
        },
        {
          "speaker": "rio",
          "name": "Río",
          "animation": "bounce",
          "text": "¡Y yo traigo la velocidad! Las palabras nuevas, las que se inventan cada día, las que todavía no están en ningún diccionario.",
          "target": [
            "palabras nuevas",
            "se inventan"
          ]
        },
        {
          "speaker": "candelaria",
          "name": "Candelaria",
          "animation": "fade-in",
          "text": "Yo traigo el {pool:eco.sound} entre las palabras. Porque a veces lo que no se dice es más elocuente que lo dicho.",
          "target": [
            "silencio",
            "elocuente"
          ]
        },
        {
          "speaker": "yaguara",
          "name": "Yaguará",
          "animation": "glow",
          "text": "Viajero, el mapa tiene una coordenada vacía. Es la tuya. ¿Qué voz traes tú?",
          "interaction": {
            "type": "pick",
            "options": [
              "La voz de quien aprendió escuchando todas las demás.",
              "Una voz que no tiene territorio.",
              "Ninguna voz."
            ],
            "answer": "La voz de quien aprendió escuchando todas las demás."
          }
        },
        {
          "speaker": "narrator",
          "name": "Narrador",
          "animation": "glow",
          "text": "El mapa se completa. No con una voz única, sino con la capacidad de habitar todas. Eso es el C2: la casa entera del idioma."
        }
      ]
    },
    {
      "_template": {
        "id": "T08_listening_pragmatic_intent",
        "layer": "narrative",
        "order": 8,
        "description": "Advanced pragmatic listening: identify indirect speech acts, implicature, and face-saving strategies.",
        "spiralReturn": [
          5,
          13
        ],
        "inputModes": [
          "choice",
          "typing"
        ],
        "ecosystemSlots": [
          "place"
        ]
      },
      "type": "listening",
      "label": "Escuchar",
      "instruction": "Identifica la intención pragmática detrás de lo que se dice en {pool:eco.place}.",
      "questions": [
        {
          "audio": "No es que no me guste tu propuesta, pero quizás podríamos considerar otras alternativas.",
          "question": "¿Cuál es la verdadera intención?",
          "answer": "Rechazar la propuesta de forma cortés e indirecta (atenuación)",
          "options": [
            "Rechazar la propuesta de forma cortés e indirecta (atenuación)",
            "Aceptar la propuesta con entusiasmo",
            "Pedir más información"
          ]
        },
        {
          "audio": "Qué bonito tu vestido. Igualito al que venden en el mercado a cinco mil pesos.",
          "question": "¿Qué acto de habla indirecto se realiza?",
          "answer": "Un cumplido envenenado: aparente elogio que en realidad menosprecia",
          "options": [
            "Un cumplido envenenado: aparente elogio que en realidad menosprecia",
            "Un cumplido sincero y espontáneo",
            "Una pregunta sobre el precio del vestido"
          ]
        },
        {
          "audio": "Bueno, yo no soy quién para opinar, pero...",
          "question": "¿Qué estrategia pragmática usa el hablante?",
          "answer": "Falsa modestia como preludio a una opinión fuerte (lítotes pragmática)",
          "options": [
            "Falsa modestia como preludio a una opinión fuerte (lítotes pragmática)",
            "Sincero reconocimiento de ignorancia",
            "Deseo de no participar en la conversación"
          ]
        }
      ]
    },
    {
      "_template": {
        "id": "T09_flashnote_register_terms",
        "layer": "core",
        "order": 9,
        "description": "Core vocabulary: register, dialect, sociolect, idiolect — the metalanguage of variation.",
        "spiralReturn": [
          3,
          8
        ],
        "inputModes": [
          "choice"
        ],
        "ecosystemSlots": [
          "place"
        ]
      },
      "type": "flashnote",
      "label": "Palabras",
      "instruction": "Reconoce la terminología sociolingüística en {pool:eco.place}.",
      "note": "diatopía",
      "question": "¿Qué estudia la diatopía?",
      "answer": "La variación lingüística según la región geográfica del hablante.",
      "options": [
        "La variación lingüística según la región geográfica del hablante.",
        "La variación según la clase social.",
        "La variación según la edad del hablante."
      ]
    },
    {
      "_template": {
        "id": "T10_fill_register_markers",
        "layer": "core",
        "order": 10,
        "description": "Identify and insert the correct register marker in context: colloquial, formal, literary.",
        "spiralReturn": [
          3,
          8
        ],
        "inputModes": [
          "choice",
          "drag",
          "typing",
          "voice"
        ],
        "ecosystemSlots": [
          "nature"
        ]
      },
      "type": "fill",
      "label": "Completar",
      "grammar": [
        "register markers"
      ],
      "instruction": "Completa con la expresión apropiada al registro indicado.",
      "tip": {
        "title": "Marcadores de registro",
        "lines": [
          "Coloquial: pues, ¿cierto?, vale, mira, oye",
          "Formal: cabe señalar, en lo que respecta a, por consiguiente",
          "Literario: acaso, empero, apenas si, como quien dice"
        ]
      },
      "questions": [
        {
          "sentence": "[FORMAL] ___ que la propuesta carece de sustento empírico.",
          "answer": "Cabe señalar",
          "options": [
            "Cabe señalar",
            "Oye, mira",
            "Acaso"
          ]
        },
        {
          "sentence": "[COLOQUIAL] ___, es que la cosa no es tan fácil, ¿me entiendes?",
          "answer": "Pues mira",
          "options": [
            "Pues mira",
            "Permítame indicar",
            "En la penumbra del verbo"
          ]
        },
        {
          "sentence": "[LITERARIO] ___ la palabra, al caer, supiera dónde será {pool:eco.nature}.",
          "answer": "Acaso",
          "options": [
            "Acaso",
            "O sea",
            "En consecuencia"
          ]
        },
        {
          "sentence": "[FORMAL] ___ a la variación diatópica, se observan diferencias fonéticas significativas.",
          "answer": "En lo que respecta",
          "options": [
            "En lo que respecta",
            "Pues vea",
            "Cual espejo roto"
          ]
        },
        {
          "sentence": "[COLOQUIAL] Uno habla como le ___, y ya, ___, no hay más vuelta.",
          "answer": "enseñaron, ¿cierto?",
          "options": [
            "enseñaron, ¿cierto?",
            "instruyeron, por consiguiente",
            "dictaron, empero"
          ]
        }
      ]
    },
    {
      "_template": {
        "id": "T11_fill_dialect_features",
        "layer": "core",
        "order": 11,
        "description": "Identify dialectal features: phonetic, lexical, morphological differences across Colombian varieties.",
        "spiralReturn": [
          4,
          11
        ],
        "inputModes": [
          "choice",
          "drag",
          "typing",
          "voice"
        ],
        "ecosystemSlots": [
          "place"
        ]
      },
      "type": "fill",
      "label": "Completar",
      "grammar": [
        "dialectal variation"
      ],
      "instruction": "Selecciona la forma dialectal correspondiente a cada región en {pool:eco.place}.",
      "tip": {
        "title": "Rasgos dialectales colombianos",
        "lines": [
          "Costeño: aspiración de /s/, voseo esporádico, léxico caribeño (vale, eche)",
          "Paisa: ustedeo generalizado, voseo íntimo, muletillas (pues, ¿cierto?)",
          "Rolo: distinción usted/tú estricta, entonación descendente, hipercorrección"
        ]
      },
      "questions": [
        {
          "sentence": "En el habla costeña, la frase 'Estás listo' se articula frecuentemente como ___.",
          "answer": "'Ehtáh lihto' (aspiración de /s/ final)",
          "options": [
            "'Ehtáh lihto' (aspiración de /s/ final)",
            "'Estás listo' (sin cambio)",
            "'Estái listo' (voseo)"
          ]
        },
        {
          "sentence": "Un paisa diría: 'Venga ___, siéntese, que le cuento.'",
          "answer": "pues",
          "options": [
            "pues",
            "vale",
            "oiga"
          ]
        },
        {
          "sentence": "El ustedeo generalizado es rasgo típico del habla ___.",
          "answer": "paisa",
          "options": [
            "paisa",
            "costeña",
            "rola"
          ]
        },
        {
          "sentence": "La aspiración de /s/ implosiva es rasgo fonético del español ___.",
          "answer": "caribeño (costeño)",
          "options": [
            "caribeño (costeño)",
            "andino (rolo)",
            "antioqueño (paisa)"
          ]
        },
        {
          "sentence": "La distinción estricta entre tú (confianza) y usted (respeto) es típica del habla ___.",
          "answer": "bogotana (rola)",
          "options": [
            "bogotana (rola)",
            "costeña",
            "paisa"
          ]
        }
      ]
    },
    {
      "_template": {
        "id": "T12_pair_register_equivalents",
        "layer": "core",
        "order": 12,
        "description": "Match the same concept expressed in three registers: colloquial, formal, literary.",
        "spiralReturn": [
          3,
          8
        ],
        "inputModes": [
          "choice",
          "drag"
        ],
        "ecosystemSlots": [
          "place"
        ]
      },
      "type": "pair",
      "label": "Emparejar",
      "instruction": "Une cada expresión coloquial con su equivalente formal en {pool:eco.place}.",
      "pairs": [
        [
          "Eso está tenaz (coloquial)",
          "La situación es crítica (formal)"
        ],
        [
          "¡Qué nota! (coloquial)",
          "Resulta sumamente interesante (formal)"
        ],
        [
          "Está mamado (coloquial)",
          "Se encuentra fatigado (formal)"
        ],
        [
          "Pilas con eso (coloquial)",
          "Conviene prestar atención (formal)"
        ],
        [
          "No hay de otra (coloquial)",
          "No existe alternativa viable (formal)"
        ],
        [
          "Eso es un camello (coloquial)",
          "La tarea es ardua (formal)"
        ]
      ]
    },
    {
      "_template": {
        "id": "T13_pair_dialect_lexicon",
        "layer": "core",
        "order": 13,
        "description": "Match dialectal terms across Colombian regions: same referent, different words.",
        "spiralReturn": [
          5,
          13
        ],
        "inputModes": [
          "choice",
          "drag"
        ],
        "ecosystemSlots": [
          "place"
        ]
      },
      "type": "pair",
      "label": "Emparejar",
      "instruction": "Une cada término regional con su sinónimo de otra región en {pool:eco.place}.",
      "pairs": [
        [
          "chévere (Colombia general)",
          "bacano (costeño)"
        ],
        [
          "man (rolo)",
          "pelao (costeño)"
        ],
        [
          "parcero (paisa)",
          "llave (rolo)"
        ],
        [
          "guayabo (paisa/rolo)",
          "ratón (costeño)"
        ],
        [
          "berraco (paisa)",
          "verraco (variante generalizada)"
        ],
        [
          "tinto (andino)",
          "tintico (diminutivo afectivo)"
        ]
      ]
    },
    {
      "_template": {
        "id": "T14_builder_formal_register",
        "layer": "core",
        "order": 14,
        "description": "Build a formal-register sentence from disordered fragments. Academic discourse construction.",
        "spiralReturn": [
          4,
          11
        ],
        "inputModes": [
          "drag",
          "typing"
        ],
        "ecosystemSlots": [
          "place"
        ]
      },
      "type": "builder",
      "label": "Construir",
      "instruction": "Ordena los fragmentos para formar una oración de registro formal-académico en {pool:eco.place}.",
      "words": [
        "En lo que respecta",
        "a la variación diatópica",
        "del español colombiano,",
        "cabe destacar",
        "la coexistencia",
        "de múltiples sistemas fonológicos",
        "en un mismo territorio nacional."
      ],
      "answer": "En lo que respecta a la variación diatópica del español colombiano, cabe destacar la coexistencia de múltiples sistemas fonológicos en un mismo territorio nacional."
    },
    {
      "_template": {
        "id": "T15_builder_literary_register",
        "layer": "core",
        "order": 15,
        "description": "Build a literary-register sentence. Poetic syntax, inversion, imagery.",
        "spiralReturn": [
          5,
          13
        ],
        "inputModes": [
          "drag",
          "typing"
        ],
        "ecosystemSlots": [
          "place"
        ]
      },
      "type": "builder",
      "label": "Construir",
      "instruction": "Ordena los fragmentos para formar una oración de registro literario en {pool:eco.place}.",
      "words": [
        "No es la lengua",
        "la que habita al hombre,",
        "sino el hombre",
        "quien se deja habitar",
        "por las voces",
        "de quienes lo precedieron."
      ],
      "answer": "No es la lengua la que habita al hombre, sino el hombre quien se deja habitar por las voces de quienes lo precedieron."
    },
    {
      "_template": {
        "id": "T16_builder_colloquial_register",
        "layer": "core",
        "order": 16,
        "description": "Reconstruct a colloquial utterance with its markers, elisiones, and discourse particles.",
        "spiralReturn": [
          3,
          8
        ],
        "inputModes": [
          "drag",
          "typing"
        ],
        "ecosystemSlots": [
          "place"
        ]
      },
      "type": "builder",
      "label": "Construir",
      "instruction": "Ordena las piezas para reconstruir la frase coloquial en {pool:eco.place}.",
      "words": [
        "Oye,",
        "parcero,",
        "es que",
        "la vaina",
        "no es así",
        "de fácil,",
        "¿me entiendes?",
        "O sea,",
        "pilas."
      ],
      "answer": "Oye, parcero, es que la vaina no es así de fácil, ¿me entiendes? O sea, pilas."
    },
    {
      "_template": {
        "id": "T17_category_register_sorting",
        "layer": "core",
        "order": 17,
        "description": "Sort expressions by register: colloquial, formal, literary.",
        "spiralReturn": [
          3,
          8
        ],
        "inputModes": [
          "choice",
          "drag"
        ],
        "ecosystemSlots": [
          "animal"
        ]
      },
      "type": "category",
      "label": "Clasificar",
      "instruction": "Clasifica cada expresión según su registro.",
      "categories": [
        "Coloquial",
        "Formal",
        "Literario"
      ],
      "items": [
        {
          "text": "Ajá, vale, ¿y entonces qué?",
          "category": "Coloquial"
        },
        {
          "text": "Cabe señalar que el fenómeno se manifiesta de forma heterogénea.",
          "category": "Formal"
        },
        {
          "text": "La palabra, al nacer, ya sabe que morirá en la boca de otro.",
          "category": "Literario"
        },
        {
          "text": "Pues sí, hombre, así es la cosa.",
          "category": "Coloquial"
        },
        {
          "text": "En consecuencia, resulta imperativo replantear la metodología.",
          "category": "Formal"
        },
        {
          "text": "Caminaban las sílabas como {pool:eco.animal} cargando el peso de su significado.",
          "category": "Literario"
        }
      ]
    },
    {
      "_template": {
        "id": "T18_category_dialect_sorting",
        "layer": "core",
        "order": 18,
        "description": "Sort dialectal features by region: costeño, paisa, rolo.",
        "spiralReturn": [
          4,
          11
        ],
        "inputModes": [
          "choice",
          "drag"
        ],
        "ecosystemSlots": [
          "place"
        ]
      },
      "type": "category",
      "label": "Clasificar",
      "instruction": "Clasifica cada rasgo dialectal según la variante regional en {pool:eco.place}.",
      "categories": [
        "Costeño",
        "Paisa",
        "Rolo"
      ],
      "items": [
        {
          "text": "Aspiración de /s/ final de sílaba",
          "category": "Costeño"
        },
        {
          "text": "Ustedeo generalizado incluso entre amigos",
          "category": "Paisa"
        },
        {
          "text": "Distinción estricta usted/tú según formalidad",
          "category": "Rolo"
        },
        {
          "text": "Uso de 'vale' como muletilla de cierre",
          "category": "Costeño"
        },
        {
          "text": "Voseo íntimo (vos sabés)",
          "category": "Paisa"
        },
        {
          "text": "Tendencia a la hipercorrección fonética",
          "category": "Rolo"
        }
      ]
    },
    {
      "_template": {
        "id": "T19_translation_register",
        "layer": "core",
        "order": 19,
        "description": "Translate the same idea into different registers — not between languages, but between sociolects.",
        "spiralReturn": [
          5,
          13
        ],
        "inputModes": [
          "choice",
          "typing",
          "voice"
        ],
        "ecosystemSlots": [
          "place"
        ]
      },
      "type": "translation",
      "label": "Traducir",
      "instruction": "Traduce entre registros: expresa la misma idea en el registro indicado en {pool:eco.place}.",
      "questions": [
        {
          "prompt": "Formal → Coloquial: 'La situación es insostenible.'",
          "answer": "Esto ya no da más, hermano.",
          "options": [
            "Esto ya no da más, hermano.",
            "El estado de cosas resulta precario.",
            "La herida del mundo supura."
          ]
        },
        {
          "prompt": "Coloquial → Formal: 'Esa vaina está remal.'",
          "answer": "La situación presenta un deterioro considerable.",
          "options": [
            "La situación presenta un deterioro considerable.",
            "Está remal la cosa.",
            "La cosa sangra por dentro."
          ]
        },
        {
          "prompt": "Formal → Literario: 'El proceso de envejecimiento es irreversible.'",
          "answer": "El tiempo no desanda sus pasos: avanza como río que ignora la nostalgia.",
          "options": [
            "El tiempo no desanda sus pasos: avanza como río que ignora la nostalgia.",
            "Envejecer no tiene vuelta atrás.",
            "El proceso etario no admite reversión."
          ]
        },
        {
          "prompt": "Literario → Coloquial: 'La soledad es un país sin mapas.'",
          "answer": "La soledad es como andar perdido sin saber pa' dónde ir.",
          "options": [
            "La soledad es como andar perdido sin saber pa' dónde ir.",
            "La soledad se define como ausencia de compañía.",
            "El aislamiento constituye un estado carencial."
          ]
        }
      ]
    },
    {
      "_template": {
        "id": "T20_dictation_literary",
        "layer": "core",
        "order": 20,
        "description": "Dictation at C2: a literary sentence with subordination, inversion, and figurative language.",
        "spiralReturn": [
          5,
          13
        ],
        "inputModes": [
          "typing"
        ],
        "ecosystemSlots": [
          "place"
        ]
      },
      "type": "dictation",
      "label": "Dictado",
      "instruction": "Escucha y escribe. Atención a la puntuación y la ortografía en {pool:eco.place}.",
      "audio": "No es que las palabras nos falten, sino que a veces somos nosotros quienes les fallamos a las palabras.",
      "answer": "No es que las palabras nos falten, sino que a veces somos nosotros quienes les fallamos a las palabras."
    },
    {
      "_template": {
        "id": "T21_dictation_dialectal",
        "layer": "core",
        "order": 21,
        "description": "Dictation of a dialectal utterance: transcribe oral features into written standard.",
        "spiralReturn": [
          4,
          11
        ],
        "inputModes": [
          "typing"
        ],
        "ecosystemSlots": [
          "place"
        ]
      },
      "type": "dictation",
      "label": "Dictado",
      "instruction": "Escucha la variante oral y escríbela en español estándar en {pool:eco.place}.",
      "audio": "Oiga, pues, ¿usted no se ha dado cuenta de que aquí la gente habla así porque así le nace del alma?",
      "answer": "Oiga, pues, ¿usted no se ha dado cuenta de que aquí la gente habla así porque así le nace del alma?"
    },
    {
      "_template": {
        "id": "T22_par_minimo_register",
        "layer": "core",
        "order": 22,
        "description": "Minimal pairs across registers: same word, different pragmatic weight.",
        "spiralReturn": [
          5,
          13
        ],
        "inputModes": [
          "choice"
        ],
        "ecosystemSlots": [
          "place"
        ]
      },
      "type": "par_minimo",
      "label": "Par mínimo",
      "instruction": "Escucha ambas versiones. ¿Cuál pertenece al registro indicado? En {pool:eco.place}.",
      "pairs": [
        {
          "wordA": "Cabe destacar que... (formal)",
          "wordB": "Mira que... (coloquial)",
          "correct": "A",
          "hint": "[FORMAL] ___"
        },
        {
          "wordA": "La vaina es que... (coloquial)",
          "wordB": "La cuestión estriba en que... (formal)",
          "correct": "B",
          "hint": "[FORMAL] ___"
        },
        {
          "wordA": "Acaso la memoria sea un espejo roto (literario)",
          "wordB": "A lo mejor uno no recuerda bien (coloquial)",
          "correct": "A",
          "hint": "[LITERARIO] ___"
        },
        {
          "wordA": "No obstante lo anterior (formal)",
          "wordB": "Pero bueno (coloquial)",
          "correct": "B",
          "hint": "[COLOQUIAL] ___"
        }
      ]
    },
    {
      "_template": {
        "id": "T23_fill_pragmatic_markers",
        "layer": "core",
        "order": 23,
        "description": "Insert pragmatic markers: hedges, boosters, face-saving devices.",
        "spiralReturn": [
          3,
          8
        ],
        "inputModes": [
          "choice",
          "drag",
          "typing",
          "voice"
        ],
        "ecosystemSlots": [
          "place"
        ]
      },
      "type": "fill",
      "label": "Completar",
      "grammar": [
        "pragmatic competence"
      ],
      "instruction": "Inserta el marcador pragmático apropiado en {pool:eco.place}.",
      "tip": {
        "title": "Marcadores pragmáticos",
        "lines": [
          "Atenuadores: digamos, en cierto modo, por así decirlo",
          "Intensificadores: sin duda, evidentemente, categóricamente",
          "Protección de imagen: con todo respeto, si me permite, no es que..."
        ]
      },
      "questions": [
        {
          "sentence": "Su argumento es, ___, algo reduccionista.",
          "answer": "por así decirlo",
          "options": [
            "por así decirlo",
            "categóricamente",
            "con todo respeto"
          ]
        },
        {
          "sentence": "___, la evidencia apunta en una sola dirección.",
          "answer": "Sin duda",
          "options": [
            "Sin duda",
            "Digamos",
            "Si me permite"
          ]
        },
        {
          "sentence": "___, pero creo que hay un error en su razonamiento.",
          "answer": "Con todo respeto",
          "options": [
            "Con todo respeto",
            "Evidentemente",
            "Por así decirlo"
          ]
        },
        {
          "sentence": "Es, ___, una forma diferente de ver el asunto.",
          "answer": "digamos",
          "options": [
            "digamos",
            "categóricamente",
            "sin duda"
          ]
        },
        {
          "sentence": "___ yo no esté de acuerdo, pero me parece que deberíamos reconsiderar.",
          "answer": "No es que",
          "options": [
            "No es que",
            "Sin duda",
            "Evidentemente"
          ]
        }
      ]
    },
    {
      "_template": {
        "id": "T24_fill_sociolinguistic",
        "layer": "core",
        "order": 24,
        "description": "Fill in sociolinguistic terminology: register, variety, diglossia, code-switching.",
        "spiralReturn": [
          4,
          11
        ],
        "inputModes": [
          "choice",
          "drag",
          "typing",
          "voice"
        ],
        "ecosystemSlots": [
          "place"
        ]
      },
      "type": "fill",
      "label": "Completar",
      "grammar": [
        "sociolinguistic metalanguage"
      ],
      "instruction": "Completa con el término sociolingüístico correcto en {pool:eco.place}.",
      "questions": [
        {
          "sentence": "El cambio entre dos lenguas o variantes en una misma conversación se denomina ___.",
          "answer": "alternancia de código",
          "options": [
            "alternancia de código",
            "diglosia",
            "diatopía"
          ]
        },
        {
          "sentence": "La variación lingüística según la región geográfica es la variación ___.",
          "answer": "diatópica",
          "options": [
            "diatópica",
            "diastrática",
            "diafásica"
          ]
        },
        {
          "sentence": "La variación según el nivel sociocultural del hablante es la variación ___.",
          "answer": "diastrática",
          "options": [
            "diastrática",
            "diatópica",
            "diafásica"
          ]
        },
        {
          "sentence": "La variación según la situación comunicativa (formal/informal) es la variación ___.",
          "answer": "diafásica",
          "options": [
            "diafásica",
            "diatópica",
            "diastrática"
          ]
        },
        {
          "sentence": "El habla particular e irrepetible de cada individuo se llama ___.",
          "answer": "idiolecto",
          "options": [
            "idiolecto",
            "sociolecto",
            "dialecto"
          ]
        }
      ]
    },
    {
      "_template": {
        "id": "T25_cartografo_linguistic_atlas",
        "layer": "skill",
        "order": 25,
        "description": "Map the linguistic atlas: place dialectal features on a conceptual map of Colombian regions.",
        "spiralReturn": [
          8,
          21
        ],
        "inputModes": [
          "choice"
        ],
        "ecosystemSlots": [
          "place"
        ]
      },
      "type": "cartografo",
      "label": "Cartógrafo",
      "instruction": "Ubica cada rasgo dialectal en el mapa lingüístico.",
      "audio": "El español colombiano no es uno: es un archipiélago de hablas. En la costa, la /s/ se aspira. En Antioquia, el usted abraza. En Bogotá, el tú distingue.",
      "replayLimit": 3,
      "gridLabels": [
        "Costa Caribe",
        "Antioquia/Eje Cafetero",
        "Bogotá/Altiplano",
        "Pacífico",
        "Llanos",
        "Amazonía"
      ],
      "questions": [
        {
          "q": "¿Dónde se aspira la /s/ implosiva como rasgo sistemático?",
          "options": [
            "Costa Caribe",
            "Bogotá/Altiplano",
            "Antioquia/Eje Cafetero"
          ],
          "answer": "Costa Caribe"
        },
        {
          "q": "¿Dónde predomina el ustedeo generalizado, incluso entre amigos?",
          "options": [
            "Antioquia/Eje Cafetero",
            "Bogotá/Altiplano",
            "Costa Caribe"
          ],
          "answer": "Antioquia/Eje Cafetero"
        },
        {
          "q": "¿Dónde se mantiene la distinción estricta usted/tú?",
          "options": [
            "Bogotá/Altiplano",
            "Costa Caribe",
            "Llanos"
          ],
          "answer": "Bogotá/Altiplano"
        }
      ]
    },
    {
      "_template": {
        "id": "T26_ritmo_literary_prose",
        "layer": "skill",
        "order": 26,
        "description": "Feel the rhythm of literary prose: stress patterns in complex words of the C2 register.",
        "spiralReturn": [
          5,
          13
        ],
        "inputModes": [
          "choice"
        ]
      },
      "type": "ritmo",
      "label": "Ritmo",
      "instruction": "¿Dónde cae el golpe fuerte? Palabras del registro C2.",
      "words": [
        {
          "word": "interlocutor",
          "syllables": [
            "in",
            "ter",
            "lo",
            "cu",
            "tor"
          ],
          "stressIndex": 4,
          "pattern": "aguda"
        },
        {
          "word": "pragmática",
          "syllables": [
            "prag",
            "má",
            "ti",
            "ca"
          ],
          "stressIndex": 1,
          "pattern": "esdrújula"
        },
        {
          "word": "sociolecto",
          "syllables": [
            "so",
            "cio",
            "lec",
            "to"
          ],
          "stressIndex": 2,
          "pattern": "llana"
        },
        {
          "word": "diatopía",
          "syllables": [
            "dia",
            "to",
            "pí",
            "a"
          ],
          "stressIndex": 2,
          "pattern": "llana"
        },
        {
          "word": "idiolecto",
          "syllables": [
            "i",
            "dio",
            "lec",
            "to"
          ],
          "stressIndex": 2,
          "pattern": "llana"
        }
      ]
    },
    {
      "_template": {
        "id": "T27_susurro_three_registers",
        "layer": "skill",
        "order": 27,
        "description": "Whisper exercise: hear the same idea in three registers, reconstruct the literary version from memory.",
        "spiralReturn": [
          5,
          13
        ],
        "inputModes": [
          "typing"
        ],
        "ecosystemSlots": [
          "sound"
        ]
      },
      "type": "susurro",
      "label": "Susurro",
      "instruction": "Escucha el {pool:eco.sound} literario. Reconstruye la frase exacta.",
      "audio": "La lengua no se posee: se habita como se habita una casa ajena que, con el tiempo, reconoce tus pasos.",
      "keywords": [
        "lengua",
        "posee",
        "habita",
        "casa",
        "ajena",
        "reconoce",
        "pasos"
      ],
      "minMatch": 5,
      "silenceDuration": 8000
    },
    {
      "_template": {
        "id": "T28_conjugation_subjunctive_mastery",
        "layer": "skill",
        "order": 28,
        "description": "Full subjunctive mastery across all tenses: present, imperfect, pluperfect, future (archaic).",
        "spiralReturn": [
          5,
          13
        ],
        "inputModes": [
          "choice",
          "drag",
          "typing",
          "voice"
        ],
        "ecosystemSlots": [
          "place"
        ]
      },
      "type": "conjugation",
      "label": "Conjugar",
      "instruction": "Completa la conjugación en el modo y tiempo indicados en {pool:eco.place}.",
      "questions": [
        {
          "verb": "habitar (pres. subj.)",
          "subject": "que yo",
          "answer": "habite",
          "options": [
            "habite",
            "habito",
            "habitara"
          ]
        },
        {
          "verb": "reconocer (imp. subj. -ra)",
          "subject": "que ella",
          "answer": "reconociera",
          "options": [
            "reconociera",
            "reconozca",
            "reconoció"
          ]
        },
        {
          "verb": "haber habitado (pluscuamp. subj.)",
          "subject": "que nosotros",
          "answer": "hubiéramos habitado",
          "options": [
            "hubiéramos habitado",
            "habíamos habitado",
            "hayamos habitado"
          ]
        },
        {
          "verb": "poseer (imp. subj. -se)",
          "subject": "que tú",
          "answer": "poseyeses",
          "options": [
            "poseyeses",
            "poseas",
            "poseías"
          ]
        },
        {
          "verb": "decir (futuro subj. arcaico)",
          "subject": "si alguien",
          "answer": "dijere",
          "options": [
            "dijere",
            "dijera",
            "diga"
          ]
        }
      ]
    },
    {
      "_template": {
        "id": "T29_cultura_colombian_dialectology",
        "layer": "skill",
        "order": 29,
        "description": "Cultural deep dive: Colombian dialectology. The history behind the variation.",
        "spiralReturn": [
          8,
          21
        ],
        "inputModes": [
          "choice"
        ],
        "ecosystemSlots": [
          "place"
        ]
      },
      "type": "cultura",
      "label": "Cultura",
      "instruction": "Lee y responde.",
      "text": "Colombia es uno de los países hispanohablantes con mayor diversidad dialectal. La geografía —cordilleras, costas, selvas, llanos— aisló comunidades durante siglos, permitiendo que cada región desarrollara rasgos lingüísticos propios. El habla costeña conserva rasgos del español andaluz y canario de los colonizadores portuarios. El habla andina mantiene la /s/ implosiva y una prosodia más contenida, herencia del contacto con lenguas indígenas de altura. El habla paisa, forjada en el aislamiento montañoso de Antioquia, desarrolló un voseo propio y un ustedeo de confianza que no tiene paralelo en el resto del país.",
      "question": "¿Por qué el habla costeña comparte rasgos con el español andaluz?",
      "answer": "Porque los colonizadores que llegaron a los puertos caribeños provenían mayoritariamente de Andalucía y Canarias.",
      "options": [
        "Porque los colonizadores que llegaron a los puertos caribeños provenían mayoritariamente de Andalucía y Canarias.",
        "Porque los colombianos costeños viajaron a Andalucía.",
        "Porque el español andaluz es más fácil de pronunciar."
      ]
    },
    {
      "_template": {
        "id": "T30_cartografo_register_map",
        "layer": "skill",
        "order": 30,
        "description": "Map registers to social situations: which register fits which context.",
        "spiralReturn": [
          5,
          13
        ],
        "inputModes": [
          "choice"
        ],
        "ecosystemSlots": [
          "place"
        ]
      },
      "type": "cartografo",
      "label": "Cartógrafo",
      "instruction": "Ubica cada registro en su contexto social apropiado en {pool:eco.place}.",
      "audio": "Los registros no son mejores ni peores: son herramientas para contextos distintos. El coloquial crea intimidad. El formal crea distancia funcional. El literario crea resonancia.",
      "replayLimit": 3,
      "gridLabels": [
        "Conversación entre amigos",
        "Ponencia académica",
        "Novela publicada",
        "Carta oficial",
        "Chat de WhatsApp",
        "Discurso poético"
      ],
      "questions": [
        {
          "q": "¿Dónde usarías 'Cabe señalar que la evidencia es contundente'?",
          "options": [
            "Ponencia académica",
            "Chat de WhatsApp",
            "Conversación entre amigos"
          ],
          "answer": "Ponencia académica"
        },
        {
          "q": "¿Dónde es apropiado 'Oye, parce, ¿qué más?'?",
          "options": [
            "Conversación entre amigos",
            "Carta oficial",
            "Novela publicada"
          ],
          "answer": "Conversación entre amigos"
        },
        {
          "q": "¿Dónde encaja 'Las palabras caían como hojas sobre el agua inmóvil'?",
          "options": [
            "Novela publicada",
            "Carta oficial",
            "Chat de WhatsApp"
          ],
          "answer": "Novela publicada"
        }
      ]
    },
    {
      "_template": {
        "id": "T31_susurro_dialectal",
        "layer": "skill",
        "order": 31,
        "description": "Whisper exercise with dialectal speech: decode a costeño whisper.",
        "spiralReturn": [
          4,
          11
        ],
        "inputModes": [
          "typing"
        ],
        "ecosystemSlots": [
          "sound"
        ]
      },
      "type": "susurro",
      "label": "Susurro",
      "instruction": "Escucha el {pool:eco.sound} costeño. Transcribe lo que dice.",
      "audio": "Mira, vale, la cosa eh que aquí la gente habla como le nace, y eso no tiene na' de malo, ¿oíhte?",
      "keywords": [
        "mira",
        "vale",
        "gente",
        "habla",
        "nace",
        "malo"
      ],
      "minMatch": 4,
      "silenceDuration": 7000
    },
    {
      "_template": {
        "id": "T32_ritmo_dialectal_prosody",
        "layer": "skill",
        "order": 32,
        "description": "Rhythm of dialectal prosody: feel the different cadences of costeño, paisa, rolo speech.",
        "spiralReturn": [
          5,
          13
        ],
        "inputModes": [
          "choice"
        ]
      },
      "type": "ritmo",
      "label": "Ritmo",
      "instruction": "Identifica el patrón prosódico de cada variante.",
      "words": [
        {
          "word": "¿Cierto? (paisa)",
          "syllables": [
            "¿Cier",
            "to?"
          ],
          "stressIndex": 0,
          "pattern": "llana — entonación ascendente final"
        },
        {
          "word": "Vale (costeño)",
          "syllables": [
            "Va",
            "le"
          ],
          "stressIndex": 0,
          "pattern": "llana — entonación descendente suave"
        },
        {
          "word": "O sea (rolo)",
          "syllables": [
            "O",
            "se",
            "a"
          ],
          "stressIndex": 1,
          "pattern": "llana — entonación plana, precisa"
        },
        {
          "word": "Eche (costeño)",
          "syllables": [
            "E",
            "che"
          ],
          "stressIndex": 0,
          "pattern": "llana — exclamativa, apertura vocálica"
        },
        {
          "word": "Pues (paisa)",
          "syllables": [
            "Pues"
          ],
          "stressIndex": 0,
          "pattern": "monosílaba — alargamiento vocálico"
        }
      ]
    },
    {
      "_template": {
        "id": "T33_cronica_my_register",
        "layer": "advanced",
        "order": 33,
        "description": "Write a crónica exploring your own voice: what register do you inhabit? What dialect shaped you?",
        "spiralReturn": [],
        "inputModes": [
          "typing"
        ]
      },
      "type": "cronica",
      "label": "Crónica",
      "prompt": "Escribe sobre tu propia voz. ¿Qué registro usas cuando hablas con amigos? ¿Y con desconocidos? ¿Hay palabras que solo existen en tu variante, en tu familia, en tu barrio? El mapa de las voces tiene un espacio vacío: el tuyo. Llénalo. Escribe en el registro que sientas más propio, luego reescribe un fragmento en otro registro.",
      "placeholder": "Cuando hablo con los míos, las palabras saben a...",
      "minWords": 80,
      "maxWords": 300,
      "scaffoldType": "free",
      "storyKey": "cronica_dest49",
      "vocabularyHints": [
        "registro",
        "variante",
        "dialecto",
        "coloquial",
        "formal",
        "literario",
        "idiolecto",
        "sociolecto",
        "pragmática",
        "diatopía",
        "código",
        "alternancia",
        "entonación",
        "prosodia"
      ],
      "button": "Guardar en la crónica"
    },
    {
      "_template": {
        "id": "T34_oraculo_register_future",
        "layer": "advanced",
        "order": 34,
        "description": "Oracle: predict the evolution of registers. What happens to colloquial speech in the digital age?",
        "spiralReturn": [
          8,
          21
        ],
        "inputModes": [
          "choice"
        ],
        "ecosystemSlots": [
          "place"
        ]
      },
      "type": "oraculo",
      "label": "Oráculo",
      "instruction": "Lee la visión del oráculo y responde.",
      "scene": [
        {
          "speaker": "Cóndor Viejo",
          "text": "Los registros no son estáticos. El coloquial de hoy será el formal de mañana. Lo literario de ayer es el cliché de hoy."
        },
        {
          "speaker": "Colibrí",
          "text": "¡Y lo que se escribe en redes sociales está creando un registro nuevo que no es ni oral ni escrito!"
        },
        {
          "speaker": "Yaguará",
          "text": "El mapa de las voces nunca se termina de dibujar. Siempre hay una coordenada nueva."
        }
      ],
      "options": [
        "Los registros evolucionan porque la lengua es un organismo vivo que responde a nuevos contextos comunicativos.",
        "Los registros son fijos y nunca cambian.",
        "Solo el registro formal tiene futuro."
      ],
      "answer": "Los registros evolucionan porque la lengua es un organismo vivo que responde a nuevos contextos comunicativos.",
      "explanation": "La lengua no es un museo: es un {pool:eco.place}. Los registros se transforman con cada generación, cada tecnología, cada migración."
    },
    {
      "_template": {
        "id": "T35_explorador_voice_archaeology",
        "layer": "advanced",
        "order": 35,
        "description": "Explorer: dig into the archaeology of voices. Find the ancient register beneath the modern one.",
        "spiralReturn": [
          8,
          21
        ],
        "inputModes": [
          "choice"
        ],
        "ecosystemSlots": [
          "place",
          "nature"
        ]
      },
      "type": "explorador",
      "label": "Explorador",
      "instruction": "Explora las capas arqueológicas de la lengua.",
      "locations": [
        {
          "name": "Capa 1: el habla de la calle",
          "text": "En la superficie, las palabras del día a día: parce, bacano, chimba. Nacen rápido, mueren rápido. Son el registro más vivo y más efímero.",
          "question": "¿Por qué el registro coloquial es el más efímero?",
          "answer": "Porque sus formas dependen del uso social inmediato y se renuevan constantemente.",
          "options": [
            "Porque sus formas dependen del uso social inmediato y se renuevan constantemente.",
            "Porque nadie lo escribe.",
            "Porque es incorrecto."
          ]
        },
        {
          "name": "Capa 2: el habla institucional",
          "text": "Debajo, el registro formal: por consiguiente, en virtud de, no obstante. Más lento en cambiar, anclado en textos escritos y en el prestigio social.",
          "question": "¿Qué ancla al registro formal y lo hace cambiar más lentamente?",
          "answer": "La escritura, la institucionalidad y el prestigio social que se le atribuye.",
          "options": [
            "La escritura, la institucionalidad y el prestigio social que se le atribuye.",
            "La pereza de los hablantes.",
            "La gramática perfecta."
          ]
        },
        {
          "name": "Capa 3: el habla literaria",
          "text": "En lo más hondo, el registro literario: las formas que sobreviven siglos porque alguien las hizo bellas. 'En un lugar de la Mancha' tiene más de cuatro siglos y sigue vivo.",
          "question": "¿Qué permite que el registro literario sobreviva siglos?",
          "answer": "La belleza formal y la fijación en textos canónicos que cada generación relee.",
          "options": [
            "La belleza formal y la fijación en textos canónicos que cada generación relee.",
            "La obligación escolar de memorizarlo.",
            "La corrección gramatical."
          ]
        }
      ]
    },
    {
      "_template": {
        "id": "T36_guardian_register_speed",
        "layer": "advanced",
        "order": 36,
        "description": "Guardian speed test: identify register, dialect, and pragmatic intent under time pressure.",
        "spiralReturn": [
          5,
          13
        ],
        "inputModes": [
          "choice",
          "typing",
          "voice"
        ],
        "ecosystemSlots": [
          "place"
        ]
      },
      "type": "guardian",
      "label": "Guardián",
      "instruction": "Responde con rapidez. Registros, dialectos, pragmática en {pool:eco.place}.",
      "timeLimit": 6,
      "questions": [
        {
          "prompt": "'Cabe señalar...' es marcador de registro ___.",
          "answer": "formal",
          "options": [
            "formal",
            "coloquial",
            "literario"
          ]
        },
        {
          "prompt": "'¿Cierto?' como muletilla es rasgo ___.",
          "answer": "paisa",
          "options": [
            "paisa",
            "costeño",
            "rolo"
          ]
        },
        {
          "prompt": "La variación según región se llama variación ___.",
          "answer": "diatópica",
          "options": [
            "diatópica",
            "diastrática",
            "diafásica"
          ]
        },
        {
          "prompt": "'Acaso la memoria...' pertenece al registro ___.",
          "answer": "literario",
          "options": [
            "literario",
            "formal",
            "coloquial"
          ]
        },
        {
          "prompt": "El habla individual e irrepetible de cada persona es su ___.",
          "answer": "idiolecto",
          "options": [
            "idiolecto",
            "sociolecto",
            "dialecto"
          ]
        },
        {
          "prompt": "'Con todo respeto, pero...' es una estrategia de ___.",
          "answer": "atenuación (protección de imagen)",
          "options": [
            "atenuación (protección de imagen)",
            "intensificación",
            "alternancia de código"
          ]
        },
        {
          "prompt": "La aspiración de /s/ final es rasgo del español ___.",
          "answer": "costeño (caribeño)",
          "options": [
            "costeño (caribeño)",
            "andino (bogotano)",
            "paisa (antioqueño)"
          ]
        },
        {
          "prompt": "Alternancia de código significa cambiar entre ___.",
          "answer": "lenguas o variantes en una conversación",
          "options": [
            "lenguas o variantes en una conversación",
            "temas diferentes",
            "registros y dialectos escritos"
          ]
        }
      ]
    },
    {
      "_template": {
        "id": "T37_autoevaluacion_c2_voices",
        "layer": "meta",
        "order": 37,
        "description": "Self-assessment: can you navigate registers, dialects, and pragmatic situations at C2 level?",
        "spiralReturn": [],
        "inputModes": [
          "choice"
        ]
      },
      "type": "autoevaluacion",
      "label": "¿Qué sé?",
      "instruction": "Evalúa tu dominio del mapa de las voces.",
      "statements": [
        {
          "text": "Puedo identificar y producir tres registros: coloquial, formal y literario."
        },
        {
          "text": "Reconozco las variantes dialectales colombianas (costeño, paisa, rolo) por sus rasgos fonéticos y léxicos."
        },
        {
          "text": "Puedo cambiar de registro dentro de una misma conversación según el interlocutor."
        },
        {
          "text": "Identifico actos de habla indirectos y estrategias de atenuación e intensificación."
        },
        {
          "text": "Manejo la terminología sociolingüística: diatopía, diastratía, diafasía, idiolecto, sociolecto."
        },
        {
          "text": "Comprendo que ninguna variante es superior a otra: el mapa de las voces no tiene centro."
        }
      ],
      "reflection": "¿Qué registro sientes más natural? ¿Cuál te cuesta más? Escribe una reflexión breve."
    },
    {
      "_template": {
        "id": "T38_portafolio_voice_map",
        "layer": "meta",
        "order": 38,
        "description": "Portfolio: record yourself speaking the same idea in three registers. Evidence of C2 register mastery.",
        "spiralReturn": [],
        "inputModes": [
          "voice"
        ]
      },
      "type": "portafolio",
      "label": "Mi voz",
      "instruction": "Graba tu voz en tres registros.",
      "prompt": "Di la misma idea tres veces: una como hablarías con tu mejor amigo (coloquial), otra como la dirías en una conferencia (formal), y otra como la escribirías en un poema (literario). La idea: 'Aprender una lengua es como encontrar un mapa que no sabías que existía.' Graba las tres versiones.",
      "guidingQuestions": [
        "¿Cómo le dirías esto a un amigo en confianza?",
        "¿Cómo lo formularías ante un público académico?",
        "¿Cómo lo convertirías en imagen poética?"
      ],
      "minWords": 30
    },
    {
      "_template": {
        "id": "T39_escaperoom_voice_map",
        "layer": "meta",
        "order": 39,
        "description": "Escape room: the Map of Voices is locked behind register puzzles. Three locks, three registers.",
        "spiralReturn": [],
        "inputModes": [
          "choice",
          "typing"
        ]
      },
      "type": "escaperoom",
      "label": "Sala de enigmas",
      "instruction": "Descifra las tres cerraduras del mapa de las voces.",
      "room": {
        "name": "La sala del mapa",
        "description": "Una sala hexagonal con tres puertas. Cada puerta está grabada con un símbolo: una boca (coloquial), un sello (formal), una pluma (literario). En el centro, el mapa de las voces espera ser liberado. Para abrirlo, debes demostrar que puedes habitar los tres registros.",
        "ambience": "resonance"
      },
      "puzzles": [
        {
          "puzzleType": "riddle",
          "prompt": "Primera cerradura (boca). Traduce al registro coloquial: 'La incertidumbre epistémica es consustancial a la condición humana.'",
          "clue": "Di lo mismo como se lo dirías a un amigo en la calle.",
          "answer": "Uno nunca sabe nada seguro, parce, así es la vida.",
          "options": [
            "Uno nunca sabe nada seguro, parce, así es la vida.",
            "La incertidumbre es epistémica y consustancial.",
            "Acaso el no saber sea nuestra única certeza."
          ],
          "onSolve": "La puerta de la boca se abre. El mapa muestra las rutas coloquiales."
        },
        {
          "puzzleType": "riddle",
          "prompt": "Segunda cerradura (sello). Traduce al registro formal: 'Es que, o sea, la vaina es que uno no cacha bien qué onda con la realidad.'",
          "clue": "Formaliza esta idea para un texto académico.",
          "answer": "La aprehensión de la realidad presenta dificultades epistemológicas inherentes.",
          "options": [
            "La aprehensión de la realidad presenta dificultades epistemológicas inherentes.",
            "La realidad es una vaina difícil de cachar.",
            "Acaso la realidad sea un espejo que no refleja."
          ],
          "onSolve": "La puerta del sello se abre. El mapa muestra las rutas formales."
        },
        {
          "puzzleType": "wordlock",
          "prompt": "Tercera cerradura (pluma). Completa la frase literaria: 'La lengua no se aprende: se ___.' (7 letras, verbo que significa hacer propio un espacio)",
          "clue": "Lo que haces con una casa cuando vives en ella tanto tiempo que te reconoce.",
          "answer": "habita",
          "hint": "_ _ _ _ _ _",
          "onSolve": "La puerta de la pluma se abre. El mapa se ilumina entero. Las tres rutas convergen."
        }
      ],
      "fragment": {
        "text": "Las tres puertas abiertas revelan el mapa completo. No es un mapa de tierra: es un mapa de voces, de registros, de dialectos. Cada ruta es una forma de habitar la lengua. Y tú, viajero, puedes recorrerlas todas.",
        "questClue": "Tres cerraduras. Tres registros. Un mapa que no tiene centro porque todo punto es centro.",
        "item": "mapa-de-voces"
      }
    },
    {
      "_template": {
        "id": "T40_conjuro_all_voices",
        "layer": "meta",
        "order": 40,
        "description": "The final conjuro: speak in all three registers. Your voice IS the map.",
        "spiralReturn": [
          8,
          21
        ],
        "inputModes": [
          "voice"
        ],
        "ecosystemSlots": [
          "place"
        ]
      },
      "type": "conjuro",
      "label": "Conjuro",
      "instruction": "Di el conjuro en tres registros. Tu voz es el mapa en {pool:eco.place}.",
      "spells": [
        {
          "prompt": "Registro coloquial: Di quién eres en este viaje.",
          "answer": "Soy el que aprendió oyendo a todos, parce, y ahora traigo mi propia voz.",
          "hint": "Habla como con un amigo."
        },
        {
          "prompt": "Registro formal: Declara tu competencia lingüística.",
          "answer": "He adquirido la competencia para navegar entre registros y variantes dialectales del español.",
          "hint": "Habla como ante un tribunal."
        },
        {
          "prompt": "Registro literario: Di la verdad profunda de tu viaje.",
          "answer": "No aprendí la lengua: la lengua me aprendió a mí, me habitó, me hizo territorio de voces.",
          "hint": "Habla como si escribieras un poema."
        },
        {
          "prompt": "Ahora, las tres voces juntas en una sola frase.",
          "answer": "Soy todas las voces que escuché y ninguna de ellas: soy el mapa.",
          "hint": "Una frase que contenga todo."
        }
      ]
    }
  ],
  "departure": {
    "type": "narrative",
    "closingQuestion": "Viajero, el mapa tiene tu voz. ¿Qué harás con ella?",
    "yaguaraLine": "El mapa de las voces no tiene centro. Cada registro, cada dialecto, cada silencio es una coordenada. Y tú puedes habitarlas todas.",
    "button": "→ Tinta y territorio",
    "nextUrl": "play.html?dest=50"
  },
  "characterMeta": {
    "char_yaguara": {
      "id": "char_yaguara",
      "name": "Yaguará",
      "avatar": "img/characters/yaguara.jpg",
      "voice": "deep",
      "description": "La jaguar. Guía del viaje. En dest49, convoca a todos los guías para trazar el mapa de las voces."
    },
    "char_candelaria": {
      "id": "char_candelaria",
      "name": "Candelaria",
      "realName": "Candelaria Arango",
      "avatar": "img/characters/candelaria.jpg",
      "voice": "clear",
      "description": "Joven afro-colombiana. Aporta el silencio entre las palabras al mapa de las voces."
    },
    "char_rio": {
      "id": "char_rio",
      "name": "Río",
      "avatar": "img/characters/rio.jpg",
      "voice": "bright",
      "description": "Joven, rápido. Aporta las palabras nuevas, las que aún no están en ningún diccionario."
    },
    "char_colibri": {
      "id": "char_colibri",
      "name": "Colibrí",
      "avatar": "img/characters/colibri.jpg",
      "voice": "quick",
      "description": "Habla en registro coloquial. Marcadores regionales, cercanía, velocidad."
    },
    "char_condor_viejo": {
      "id": "char_condor_viejo",
      "name": "Cóndor Viejo",
      "avatar": "img/characters/condor-viejo.jpg",
      "voice": "solemn",
      "description": "Habla en registro formal. Distanciamiento, léxico técnico, cortesía indirecta."
    },
    "char_delfin_rosado": {
      "id": "char_delfin_rosado",
      "name": "Delfín Rosado",
      "avatar": "img/characters/delfin-rosado.jpg",
      "voice": "fluid",
      "description": "Habla en registro literario. Imágenes, polisemia, ritmo poético."
    },
    "char_tortuga_marina": {
      "id": "char_tortuga_marina",
      "name": "Tortuga Marina",
      "avatar": "img/characters/tortuga-marina.jpg",
      "voice": "slow",
      "description": "Habla antigua, paciente. Las palabras que tardan en llegar porque vienen de muy hondo."
    }
  }
}